{
    "202202": {
        "Staff": [
            {
                "name": "סגל-פרץ תמר",
                "email": "tamarps@technion.ac.il",
                "title": "מרצה - אחראי מקצוע"
            },
            {
                "name": "גזית עוז",
                "email": "ozg@technion.ac.il",
                "title": "מרצה"
            },
            {
                "name": "נעמת לילך",
                "email": "slily91@campus.technion.ac.il",
                "title": ""
            }
        ],
        "Exam_A": {
            "students": "34",
            "passFail": "32\/2",
            "passPercent": "94",
            "min": "37",
            "max": "96",
            "average": "73.676",
            "median": "74"
        },
        "Final_A": {
            "students": "34",
            "passFail": "33\/1",
            "passPercent": "97",
            "min": "47",
            "max": "96",
            "average": "82.529",
            "median": "84"
        },
        "Finals": {
            "students": "41",
            "passFail": "41\/0",
            "passPercent": "100",
            "min": "61",
            "max": "96",
            "average": "83.206",
            "median": "84"
        }
    }
}