{"202201":{"Staff":[{"name":"נאמן ישראל","email":"syneeman@bezeqint.net,yisraeln@technion.ac.il","title":"מרצה - אחראי מקצוע"}],"Finals":{"students":"15","passFail":"15\/0","passPercent":"100","min":"76","max":"100","average":"92.267","median":"92"}},"202102":{"Staff":[{"name":"נאמן ישראל","email":"syneeman@bezeqint.net,yisraeln@technion.ac.il","title":"מרצה - אחראי מקצוע"}],"Final_A":{"students":"15","passFail":"15\/0","passPercent":"100","min":"61","max":"100","average":"94.2","median":"96"},"Finals":{"students":"16","passFail":"16\/0","passPercent":"100","min":"61","max":"100","average":"94.312","median":"96"}},"202002":{"Staff":[{"name":"אלמוגי בת-אל","email":"academic@int.technion.ac.il,batella@technion.ac.il","title":"מרצה - אחראי מקצוע"}],"Final_A":{"students":"17","passFail":"17\/0","passPercent":"100","min":"60","max":"100","average":"89.059","median":"96"},"Finals":{"students":"17","passFail":"17\/0","passPercent":"100","min":"64","max":"100","average":"92.118","median":"96"}},"201901":{"Staff":[{"name":"נאמן ישראל","email":"syneeman@bezeqint.net","title":"מרצה - אחראי מקצוע"},{"name":"אלמוגי בת-אל","email":"academic@int.technion.ac.il","title":"מרצה"}],"Final_A":{"students":"13","passFail":"13\/0","passPercent":"100","min":"69","max":"100","average":"87","median":"87"},"Finals":{"students":"14","passFail":"14\/0","passPercent":"100","min":"69","max":"100","average":"87.214","median":"87.5"}},"201701":{"Staff":[{"name":"נאמן ישראל","email":"syneeman@bezeqint.net","title":"מרצה - אחראי מקצוע"}],"Finals":{"students":"17","passFail":"16\/1","passPercent":"94","min":"48","max":"100","average":"81.176","median":"78"}},"201602":{"Staff":[{"name":"נאמן ישראל","email":"syneeman@bezeqint.net","title":"מרצה - אחראי מקצוע"}],"Finals":{"students":"35","passFail":"35\/0","passPercent":"100","min":"56","max":"100","average":"83.657","median":"85"}}}