{"202401":{"Staff":[{"name":"קרופורד ניקולאס","email":"nickc@technion.ac.il","title":"מרצה - אחראי מקצוע"}],"Exam_A":{"students":"28","passFail":"18\/10","passPercent":"64","min":"20","max":"100","average":"64.821","median":"67.5"},"Final_A":{"students":"29","passFail":"26\/3","passPercent":"90","min":"42","max":"100","average":"74.793","median":"76"},"Exam_B":{"students":"32","passFail":"24\/8","passPercent":"75","min":"34","max":"93","average":"69.469","median":"69"},"Final_B":{"students":"32","passFail":"31\/1","passPercent":"97","min":"52","max":"94","average":"76","median":"74.5"},"Finals":{"students":"46","passFail":"44\/2","passPercent":"96","min":"51","max":"100","average":"78.5","median":"80.5"}},"202302":{"Staff":[{"name":"רותם לירן","email":"lrotem@technion.ac.il","title":"מרצה - אחראי מקצוע"}],"Exam_A":{"students":"20","passFail":"15\/5","passPercent":"75","min":"23","max":"98","average":"68.95","median":"74"},"Final_A":{"students":"20","passFail":"17\/3","passPercent":"85","min":"23","max":"99","average":"72.05","median":"77.5"},"Finals":{"students":"24","passFail":"23\/1","passPercent":"96","min":"45","max":"99","average":"77.625","median":"78"}},"202301":{"Staff":[{"name":"דניאלי יואב","email":"yoavd@campus.technion.ac.il","title":"מתרגל"},{"name":"פינסקי רוס","email":"pinsky@math.technion.ac.il,pinsky@technion.ac.il","title":"מרצה - אחראי מקצוע"}],"Exam_A":{"students":"74","passFail":"70\/4","passPercent":"95","min":"37","max":"100","average":"82.378","median":"84"},"Final_A":{"students":"74","passFail":"72\/2","passPercent":"97","min":"43","max":"100","average":"84.473","median":"86"},"Exam_B":{"students":"17","passFail":"13\/4","passPercent":"76","min":"17","max":"100","average":"67.941","median":"72"},"Final_B":{"students":"17","passFail":"14\/3","passPercent":"82","min":"25","max":"100","average":"73.235","median":"79"},"Finals":{"students":"82","passFail":"79\/3","passPercent":"96","min":"25","max":"100","average":"84.585","median":"87"}},"202202":{"Staff":[{"name":"מילמן עמנואל","email":"emilman@technion.ac.il","title":"מרצה - אחראי מקצוע"}],"Exam_A":{"students":"20","passFail":"11\/9","passPercent":"55","min":"8","max":"89","average":"44.75","median":"55"},"Final_A":{"students":"20","passFail":"11\/9","passPercent":"55","min":"8","max":"92","average":"49.65","median":"66"},"Exam_B":{"students":"15","passFail":"7\/8","passPercent":"47","min":"14","max":"97","average":"51.467","median":"46"},"Final_B":{"students":"15","passFail":"7\/8","passPercent":"47","min":"14","max":"97","average":"53.933","median":"46"},"Finals":{"students":"27","passFail":"17\/10","passPercent":"63","min":"8","max":"97","average":"53.526","median":"46"}},"202201":{"Staff":[{"name":"רוזנטל רון","email":"ron.ro@technion.ac.il","title":"מרצה - אחראי מקצוע"},{"name":"סופר אהרונוב נוי","email":"noyso@campus.technion.ac.il","title":"מתרגל - עם הרשאות מרצה אחראי"}],"Exam_A":{"students":"41","passFail":"33\/8","passPercent":"80","min":"16","max":"100","average":"73.146","median":"77"},"Final_A":{"students":"41","passFail":"34\/7","passPercent":"83","min":"16","max":"100","average":"74.561","median":"79"},"Exam_B":{"students":"27","passFail":"20\/7","passPercent":"74","min":"41","max":"100","average":"70.889","median":"68"},"Final_B":{"students":"27","passFail":"21\/6","passPercent":"78","min":"41","max":"100","average":"71.852","median":"71"},"Finals":{"students":"53","passFail":"47\/6","passPercent":"89","min":"41","max":"100","average":"78.509","median":"82"}},"202102":{"Staff":[{"name":"רותם לירן","email":"lrotem@technion.ac.il","title":"מרצה - אחראי מקצוע"}],"Exam_A":{"students":"25","passFail":"14\/11","passPercent":"56","min":"9","max":"89","average":"55.68","median":"56"},"Final_A":{"students":"25","passFail":"20\/5","passPercent":"80","min":"25","max":"92","average":"63.48","median":"63"},"Exam_B":{"students":"15","passFail":"8\/7","passPercent":"53","min":"16","max":"100","average":"56.933","median":"52"},"Final_B":{"students":"15","passFail":"10\/5","passPercent":"67","min":"28","max":"100","average":"63.067","median":"59"},"Finals":{"students":"31","passFail":"26\/5","passPercent":"84","min":"28","max":"100","average":"66.968","median":"63"}},"202101":{"Staff":[{"name":"פינסקי רוס","email":"pinsky@math.technion.ac.il,pinsky@technion.ac.il","title":"מרצה - אחראי מקצוע"},{"name":"סופר אהרונוב נוי","email":"noyso@campus.technion.ac.il","title":"מתרגל"}],"Exam_A":{"students":"89","passFail":"68\/21","passPercent":"76","min":"14","max":"100","average":"73.449","median":"79"},"Final_A":{"students":"89","passFail":"75\/14","passPercent":"84","min":"21","max":"100","average":"77.854","median":"82"},"Exam_B":{"students":"33","passFail":"15\/18","passPercent":"45","min":"0","max":"100","average":"54.848","median":"54"},"Final_B":{"students":"33","passFail":"20\/13","passPercent":"61","min":"14","max":"100","average":"60.515","median":"58"},"Exam_C":{"students":"14","passFail":"12\/2","passPercent":"86","min":"32","max":"100","average":"74.143","median":"80"},"Finals":{"students":"103","passFail":"95\/8","passPercent":"92","min":"14","max":"100","average":"80.252","median":"85"}},"202002":{"Staff":[{"name":"רותם לירן","email":"lrotem@technion.ac.il","title":"מרצה - אחראי מקצוע"},{"name":"לייבזירר שקד","email":"leibzirers@campus.technion.ac.il","title":"מתרגל"}],"Exam_A":{"students":"36","passFail":"30\/6","passPercent":"83","min":"28","max":"100","average":"73.278","median":"74.5"},"Final_A":{"students":"36","passFail":"32\/4","passPercent":"89","min":"39","max":"100","average":"76.917","median":"78"},"Exam_B":{"students":"16","passFail":"3\/13","passPercent":"19","min":"17","max":"86","average":"44.312","median":"43.5"},"Final_B":{"students":"16","passFail":"11\/5","passPercent":"69","min":"35","max":"94","average":"58.125","median":"58"},"Finals":{"students":"46","passFail":"40\/6","passPercent":"87","min":"35","max":"100","average":"74.37","median":"77"}},"202001":{"Staff":[{"name":"מאיר-וולף אדוארדו","email":"emw@technion.ac.il","title":"מרצה - אחראי מקצוע"},{"name":"לייבזירר שקד","email":"leibzirers@campus.technion.ac.il","title":"מתרגל"}],"Exam_A":{"students":"67","passFail":"41\/26","passPercent":"61","min":"9","max":"100","average":"63.164","median":"66"},"Final_A":{"students":"67","passFail":"50\/17","passPercent":"75","min":"15","max":"100","average":"69.687","median":"73"},"Exam_B":{"students":"46","passFail":"28\/18","passPercent":"61","min":"16","max":"98","average":"60.891","median":"64.5"},"Final_B":{"students":"46","passFail":"35\/11","passPercent":"76","min":"34","max":"99","average":"67.478","median":"72"},"Finals":{"students":"82","passFail":"68\/14","passPercent":"83","min":"15","max":"100","average":"73.183","median":"79"}},"201902":{"Staff":[{"name":"רותם לירן","email":"lrotem@technion.ac.il","title":"מרצה - אחראי מקצוע"}],"Exam_A":{"students":"33","passFail":"19\/14","passPercent":"58","min":"7","max":"100","average":"60.758","median":"60"},"Final_A":{"students":"33","passFail":"22\/11","passPercent":"67","min":"21","max":"100","average":"66.152","median":"66"},"Exam_B":{"students":"32","passFail":"27\/5","passPercent":"84","min":"35","max":"98","average":"73.062","median":"74"},"Final_B":{"students":"32","passFail":"30\/2","passPercent":"94","min":"45","max":"98","average":"76.5","median":"78"},"Finals":{"students":"48","passFail":"45\/3","passPercent":"94","min":"43","max":"100","average":"79.292","median":"83"}},"201901":{"Staff":[{"name":"יהודיוף אמיר","email":"yehuday@technion.ac.il","title":"מרצה - אחראי מקצוע"},{"name":"לייבזירר שקד","email":"leibzirers@campus.technion.ac.il","title":"מתרגל"}],"Final_A":{"students":"45","passFail":"35\/10","passPercent":"78","min":"13","max":"92","average":"63.289","median":"65"},"Exam_B":{"students":"41","passFail":"28\/13","passPercent":"68","min":"15","max":"94","average":"62","median":"63"},"Final_B":{"students":"41","passFail":"33\/8","passPercent":"80","min":"28","max":"95","average":"67.098","median":"68"},"Finals":{"students":"53","passFail":"44\/9","passPercent":"83","min":"28","max":"95","average":"67.887","median":"68"}},"201802":{"Staff":[{"name":"הולצמן רון","email":"holzman@technion.ac.il","title":"מרצה - אחראי מקצוע"}],"Exam_A":{"students":"24","passFail":"16\/8","passPercent":"67","min":"5","max":"86","average":"53.25","median":"58"},"Final_A":{"students":"24","passFail":"17\/7","passPercent":"71","min":"23","max":"87","average":"60","median":"64"},"Exam_B":{"students":"15","passFail":"9\/6","passPercent":"60","min":"8","max":"100","average":"65.133","median":"61"},"Final_B":{"students":"15","passFail":"13\/2","passPercent":"87","min":"8","max":"100","average":"68.2","median":"66"},"Finals":{"students":"30","passFail":"26\/4","passPercent":"87","min":"8","max":"100","average":"66.867","median":"67"}},"201801":{"Staff":[{"name":"מאיר-וולף אדוארדו","email":"emw@technion.ac.il","title":"מרצה - אחראי מקצוע"}],"Exam_A":{"students":"33","passFail":"23\/10","passPercent":"70","min":"23","max":"100","average":"72.848","median":"78"},"Final_A":{"students":"33","passFail":"28\/5","passPercent":"85","min":"24","max":"100","average":"74.879","median":"79"},"Exam_B":{"students":"21","passFail":"15\/6","passPercent":"71","min":"38","max":"100","average":"71.333","median":"77"},"Final_B":{"students":"21","passFail":"16\/5","passPercent":"76","min":"42","max":"100","average":"72.286","median":"77"},"Finals":{"students":"40","passFail":"35\/5","passPercent":"88","min":"42","max":"100","average":"79.325","median":"83"}},"201702":{"Staff":[{"name":"מעין יוחאי","email":"ymaayan@technion.ac.il,ymaayan@campus.technion.ac.il","title":"מרצה - אחראי מקצוע"},{"name":"אלון ליאור","email":"lioralon@campus.technion.ac.il","title":"מתרגל"}],"Exam_A":{"students":"19","passFail":"6\/13","passPercent":"32","min":"0","max":"97","average":"47","median":"46"},"Final_A":{"students":"19","passFail":"11\/8","passPercent":"58","min":"10","max":"100","average":"56.632","median":"55"},"Exam_B":{"students":"13","passFail":"7\/6","passPercent":"54","min":"15","max":"90","average":"54.154","median":"58"},"Final_B":{"students":"13","passFail":"8\/5","passPercent":"62","min":"24","max":"91","average":"57.692","median":"60"},"Finals":{"students":"21","passFail":"16\/5","passPercent":"76","min":"24","max":"100","average":"66.143","median":"69"}},"201701":{"Staff":[{"name":"פינסקי רוס","email":"pinsky@math.technion.ac.il,pinsky@technion.ac.il","title":"מרצה - אחראי מקצוע"},{"name":"קלדרון ערן","email":"calderon@technion.ac.il","title":"מתרגל"}],"Exam_A":{"students":"32","passFail":"21\/11","passPercent":"66","min":"4","max":"99","average":"63.625","median":"71"},"Final_A":{"students":"32","passFail":"21\/11","passPercent":"66","min":"5","max":"99","average":"68.438","median":"78"},"Exam_B":{"students":"18","passFail":"11\/7","passPercent":"61","min":"2","max":"97","average":"58.611","median":"59.5"},"Final_B":{"students":"18","passFail":"12\/6","passPercent":"67","min":"2","max":"97","average":"62.389","median":"63"},"Finals":{"students":"34","passFail":"28\/6","passPercent":"82","min":"2","max":"99","average":"72.794","median":"84"}},"201602":{"Staff":[{"name":"מאיר-וולף אדוארדו","email":"emw@technion.ac.il","title":"מרצה - אחראי מקצוע"},{"name":"נחום עידו","email":"idon@technion.ac.il","title":"מתרגל"}],"Exam_A":{"students":"20","passFail":"15\/5","passPercent":"75","min":"0","max":"100","average":"69.5","median":"82.5"},"Final_A":{"students":"20","passFail":"16\/4","passPercent":"80","min":"0","max":"100","average":"70.95","median":"86"},"Finals":{"students":"24","passFail":"20\/4","passPercent":"83","min":"13","max":"100","average":"72.833","median":"79"}},"201601":{"Staff":[{"name":"רוזנטל רון","email":"ron.ro@technion.ac.il","title":"מרצה - אחראי מקצוע"},{"name":"לב-ארי ענת","email":"anatleva@campus.technion.ac.il","title":"מתרגל"}],"Exam_A":{"students":"31","passFail":"27\/4","passPercent":"87","min":"22","max":"100","average":"73.032","median":"70"},"Final_A":{"students":"31","passFail":"29\/2","passPercent":"94","min":"22","max":"100","average":"75.452","median":"73"},"Exam_B":{"students":"21","passFail":"17\/4","passPercent":"81","min":"30","max":"97","average":"71.857","median":"75"},"Final_B":{"students":"21","passFail":"19\/2","passPercent":"90","min":"44","max":"97","average":"74.81","median":"79"},"Finals":{"students":"43","passFail":"41\/2","passPercent":"95","min":"44","max":"100","average":"77.442","median":"78"}},"201501":{"Staff":[{"name":"מילמן עמנואל","email":"emilman@technion.ac.il","title":"מרצה - אחראי מקצוע"},{"name":"אלון ליאור","email":"lioralon@campus.technion.ac.il","title":"מתרגל"}],"Exam_A":{"students":"33","passFail":"25\/8","passPercent":"76","min":"8","max":"97","average":"66.455","median":"70"},"Final_A":{"students":"33","passFail":"25\/8","passPercent":"76","min":"8","max":"97","average":"70.03","median":"77"},"Exam_B":{"students":"15","passFail":"6\/9","passPercent":"40","min":"7","max":"83","average":"44.533","median":"49"},"Final_B":{"students":"15","passFail":"9\/6","passPercent":"60","min":"5","max":"86","average":"55.867","median":"60"},"Finals":{"students":"37","passFail":"29\/8","passPercent":"78","min":"5","max":"97","average":"70.378","median":"77"}},"201202":{"Staff":[{"name":"הולצמן רון","email":"holzman@technion.ac.il","title":"מרצה - אחראי מקצוע"},{"name":"מעין יוחאי","email":"ymaayan@technion.ac.il,ymaayan@campus.technion.ac.il","title":"מתרגל"}],"Final_A":{"students":"23","passFail":"21\/2","passPercent":"91","min":"19","max":"100","average":"70.609","median":"64"},"Final_B":{"students":"12","passFail":"9\/3","passPercent":"75","min":"23","max":"92","average":"65.5","median":"72.5"}}}