{
    "202102": {
        "Staff": [
            {
                "name": "פרייס דן",
                "email": "danprice@technion.ac.il",
                "title": "מנחה פרויקטים  - עם הרשאות מרצה אחראי"
            }
        ],
        "Final_A": {
            "students": "19",
            "passFail": "19\/0",
            "passPercent": "100",
            "min": "92",
            "max": "99",
            "average": "96.842",
            "median": "98"
        },
        "Finals": {
            "students": "19",
            "passFail": "19\/0",
            "passPercent": "100",
            "min": "92",
            "max": "99",
            "average": "96.842",
            "median": "98"
        }
    },
    "202001": {
        "Staff": [
            {
                "name": "בלייכר מיכל",
                "email": "michalbleicher@gmail.com",
                "title": "מנחה פרויקטים  - עם הרשאות מרצה אחראי"
            },
            {
                "name": "פרייס דן",
                "email": "danprice@technion.ac.il",
                "title": ""
            },
            {
                "name": "מג'אר טליה",
                "email": "talia@technion.ac.il",
                "title": ""
            }
        ],
        "Final_A": {
            "students": "15",
            "passFail": "15\/0",
            "passPercent": "100",
            "min": "96",
            "max": "96",
            "average": "96",
            "median": "96"
        },
        "Finals": {
            "students": "19",
            "passFail": "19\/0",
            "passPercent": "100",
            "min": "96",
            "max": "96",
            "average": "96",
            "median": "96"
        }
    },
    "201901": {
        "Final_A": {
            "students": "13",
            "passFail": "13\/0",
            "passPercent": "100",
            "min": "95",
            "max": "97",
            "average": "95.308",
            "median": "95"
        },
        "Finals": {
            "students": "14",
            "passFail": "14\/0",
            "passPercent": "100",
            "min": "95",
            "max": "97",
            "average": "95.286",
            "median": "95"
        }
    }
}