{"201802":{"Staff":[{"name":"גרדר גדעון","email":"grader@technion.ac.il","title":"מרצה - אחראי מקצוע"},{"name":"מוסביצקי בר","email":"mosobar@technion.ac.il,mosobar@campus.technion.ac.il","title":"מתרגל"},{"name":"קרלין קרשובר ענת","email":"anatkarlin@campus.technion.ac.il","title":"מתרגל"}],"Exam_A":{"students":"71","passFail":"53\/18","passPercent":"75","min":"3","max":"100","average":"69.859","median":"76"},"Final_A":{"students":"71","passFail":"53\/18","passPercent":"75","min":"15","max":"100","average":"71.775","median":"77"},"Exam_B":{"students":"37","passFail":"27\/10","passPercent":"73","min":"28","max":"100","average":"66.973","median":"67"},"Final_B":{"students":"37","passFail":"28\/9","passPercent":"76","min":"28","max":"100","average":"68.189","median":"70"},"Finals":{"students":"85","passFail":"75\/10","passPercent":"88","min":"28","max":"100","average":"77.635","median":"80"}}}