{"202301":{"Staff":[{"name":"אורבך שלום","email":"saul@beachheadgroup.com","title":"מרצה - אחראי מקצוע"},{"name":"בן ענת רוחמה","email":"ruchamab@technion.ac.il","title":"סגל מנהלי - עם הרשאות מרצה אחראי"},{"name":"בן-איש שלומית","email":"shlomitb@technion.ac.il","title":"סגל מנהלי - עם הרשאות מרצה אחראי"}],"Final_A":{"students":"20","passFail":"20\/0","passPercent":"100","min":"85","max":"93","average":"89.6","median":"91"},"Finals":{"students":"27","passFail":"27\/0","passPercent":"100","min":"85","max":"93","average":"89.519","median":"90"}}}