{"202401":{"Staff":[{"name":"גולדברג יאיר","email":"yairgo@technion.ac.il","title":"מרצה - אחראי מקצוע"},{"name":"ברקוביץ' עמית","email":"amit.b@campus.technion.ac.il","title":"מתרגל - עם הרשאות מרצה אחראי"}],"Final_A":{"students":"111","passFail":"72\/39","passPercent":"65","min":"8","max":"100","average":"67.432","median":"74"},"Final_B":{"students":"53","passFail":"40\/13","passPercent":"75","min":"40","max":"100","average":"68.491","median":"70"},"Finals":{"students":"125","passFail":"105\/20","passPercent":"84","min":"19","max":"100","average":"76.169","median":"76.5"}},"202301":{"Staff":[{"name":"גולדברג יאיר","email":"yairgo@technion.ac.il","title":"מרצה - אחראי מקצוע"},{"name":"ציצלסקי עומר","email":"omercicelsky@campus.technion.ac.il","title":"מתרגל - עם הרשאות מרצה אחראי"}],"Final_A":{"students":"109","passFail":"73\/36","passPercent":"67","min":"0","max":"100","average":"60.156","median":"67"},"Final_B":{"students":"35","passFail":"29\/6","passPercent":"83","min":"42","max":"95","average":"67.086","median":"66"},"Finals":{"students":"102","passFail":"97\/5","passPercent":"95","min":"37","max":"100","average":"76.077","median":"75"}},"202203":{"Staff":[{"name":"גולדברג יאיר","email":"yairgo@technion.ac.il","title":"מרצה - אחראי מקצוע"},{"name":"נבו אבישג","email":"avishag.nevo@campus.technion.ac.il","title":"מתרגל - עם הרשאות מרצה אחראי"}],"Final_A":{"students":"","passFail":"","passPercent":"","min":"","max":"","average":"","median":""},"Finals":{"students":"","passFail":"","passPercent":"","min":"","max":"","average":"","median":""}},"202201":{"Staff":[{"name":"גולדברג יאיר","email":"yairgo@technion.ac.il","title":"מרצה - אחראי מקצוע"},{"name":"ברקוביץ' עמית","email":"amit.b@campus.technion.ac.il","title":"מתרגל - עם הרשאות מרצה אחראי"},{"name":"זיו דוד מורן","email":"moran.z@technion.ac.il","title":"סגל מנהלי - עם הרשאות מרצה אחראי"}],"Final_A":{"students":"132","passFail":"84\/48","passPercent":"64","min":"14","max":"100","average":"65.598","median":"72"},"Final_B":{"students":"72","passFail":"58\/14","passPercent":"81","min":"44","max":"95","average":"64.167","median":"62.5"},"Finals":{"students":"158","passFail":"139\/19","passPercent":"88","min":"15","max":"100","average":"72.241","median":"73.5"}},"202101":{"Staff":[{"name":"גולדברג יאיר","email":"yairgo@technion.ac.il","title":"מרצה - אחראי מקצוע"},{"name":"זיו דוד מורן","email":"moran.z@technion.ac.il","title":"סגל מנהלי - עם הרשאות מרצה אחראי"}],"Final_A":{"students":"77","passFail":"74\/3","passPercent":"96","min":"24","max":"100","average":"84.779","median":"90"},"Finals":{"students":"77","passFail":"74\/3","passPercent":"96","min":"24","max":"100","average":"84.779","median":"90"}},"202002":{"Staff":[{"name":"גולדברג יאיר","email":"yairgo@technion.ac.il","title":"מרצה - אחראי מקצוע"},{"name":"זיו דוד מורן","email":"moran.z@technion.ac.il","title":"סגל מנהלי - עם הרשאות מרצה אחראי"}],"Exam_A":{"students":"83","passFail":"59\/24","passPercent":"71","min":"0","max":"98","average":"64.518","median":"72"},"Final_A":{"students":"83","passFail":"73\/10","passPercent":"88","min":"31","max":"98","average":"77.157","median":"82"},"Exam_B":{"students":"31","passFail":"17\/14","passPercent":"55","min":"3","max":"86","average":"53.968","median":"55"},"Final_B":{"students":"31","passFail":"27\/4","passPercent":"87","min":"40","max":"91","average":"69.903","median":"72"},"Finals":{"students":"95","passFail":"90\/5","passPercent":"95","min":"32","max":"98","average":"78.726","median":"83"}},"201902":{"Staff":[{"name":"גולדברג יאיר","email":"yairgo@technion.ac.il","title":"מרצה - אחראי מקצוע"},{"name":"מדמון אורון","email":"oronmadmon@gmail.com,oronmadmon@campus.technion.ac.il","title":"מתרגל - עם הרשאות מרצה אחראי"},{"name":"זיו דוד מורן","email":"moran.z@technion.ac.il","title":"סגל מנהלי - עם הרשאות מרצה אחראי"},{"name":"אגסי זיוה","email":"aziva@ie.technion.ac.il,aziva@technion.ac.il","title":"סגל מנהלי - עם הרשאות מרצה אחראי"}],"Final_A":{"students":"63","passFail":"63\/0","passPercent":"100","min":"67","max":"100","average":"89.889","median":"92"},"Finals":{"students":"63","passFail":"63\/0","passPercent":"100","min":"67","max":"100","average":"89.889","median":"92"}},"201802":{"Staff":[{"name":"גולדברג יאיר","email":"yairgo@technion.ac.il","title":"מרצה - אחראי מקצוע"}],"Final_A":{"students":"33","passFail":"33\/0","passPercent":"100","min":"58","max":"100","average":"81.818","median":"82"},"Finals":{"students":"35","passFail":"35\/0","passPercent":"100","min":"58","max":"100","average":"84.857","median":"85"}}}