{
    "201401": {
        "Staff": [
            {
                "name": "קופרמן אלכסנדר",
                "email": "kupalex@technion.ac.il",
                "title": "מרצה - אחראי מקצוע"
            }
        ],
        "Finals": {
            "students": "29",
            "passFail": "27\/2",
            "passPercent": "93",
            "min": "12",
            "max": "100",
            "average": "79.655",
            "median": "86"
        }
    },
    "201501": {
        "Staff": [
            {
                "name": "קופרמן אלכסנדר",
                "email": "kupalex@technion.ac.il",
                "title": "מרצה - אחראי מקצוע"
            }
        ],
        "Finals": {
            "students": "",
            "passFail": "",
            "passPercent": "",
            "min": "",
            "max": "",
            "average": "",
            "median": ""
        }
    },
    "201601": {
        "Staff": [
            {
                "name": "קופרמן אלכסנדר",
                "email": "kupalex@technion.ac.il",
                "title": "מרצה - אחראי מקצוע"
            }
        ],
        "Finals": {
            "students": "",
            "passFail": "",
            "passPercent": "",
            "min": "",
            "max": "",
            "average": "",
            "median": ""
        }
    },
    "201701": {
        "Staff": [
            {
                "name": "קופרמן אלכסנדר",
                "email": "kupalex@technion.ac.il",
                "title": "מרצה - אחראי מקצוע"
            }
        ],
        "Finals": {
            "students": "",
            "passFail": "",
            "passPercent": "",
            "min": "",
            "max": "",
            "average": "",
            "median": ""
        }
    },
    "201801": {
        "Staff": [
            {
                "name": "קופרמן אלכסנדר",
                "email": "kupalex@technion.ac.il",
                "title": "מרצה - אחראי מקצוע"
            }
        ],
        "Finals": {
            "students": "",
            "passFail": "",
            "passPercent": "",
            "min": "",
            "max": "",
            "average": "",
            "median": ""
        }
    },
    "201901": {
        "Staff": [
            {
                "name": "קופרמן אלכסנדר",
                "email": "kupalex@technion.ac.il",
                "title": "מרצה - אחראי מקצוע"
            }
        ],
        "Final_A": {
            "students": "",
            "passFail": "",
            "passPercent": "",
            "min": "",
            "max": "",
            "average": "",
            "median": ""
        },
        "Finals": {
            "students": "",
            "passFail": "",
            "passPercent": "",
            "min": "",
            "max": "",
            "average": "",
            "median": ""
        }
    },
    "202001": {
        "Staff": [
            {
                "name": "קופרמן אלכסנדר",
                "email": "kupalex@technion.ac.il",
                "title": "מרצה - אחראי מקצוע"
            }
        ],
        "Final_A": {
            "students": "",
            "passFail": "",
            "passPercent": "",
            "min": "",
            "max": "",
            "average": "",
            "median": ""
        },
        "Finals": {
            "students": "",
            "passFail": "",
            "passPercent": "",
            "min": "",
            "max": "",
            "average": "",
            "median": ""
        }
    }
}