{"201901":{"Final_A":{"students":"46","passFail":"46\/0","passPercent":"100","min":"79","max":"100","average":"92.435","median":"93"},"Finals":{"students":"46","passFail":"46\/0","passPercent":"100","min":"79","max":"100","average":"92.435","median":"93"}},"201703":{"Final_A":{"students":"41","passFail":"41\/0","passPercent":"100","min":"83","max":"100","average":"92.488","median":"93"},"Finals":{"students":"41","passFail":"41\/0","passPercent":"100","min":"83","max":"100","average":"92.488","median":"93"}}}