{
    "202301": {
        "Staff": [
            {
                "name": "קליין גריגורי",
                "email": "gregy.kl@technion.ac.il",
                "title": "מרצה - אחראי מקצוע"
            }
        ],
        "Final_A": {
            "students": "78",
            "passFail": "78\/0",
            "passPercent": "100",
            "min": "88",
            "max": "100",
            "average": "93.846",
            "median": "94"
        },
        "Finals": {
            "students": "78",
            "passFail": "78\/0",
            "passPercent": "100",
            "min": "88",
            "max": "100",
            "average": "93.846",
            "median": "94"
        }
    },
    "202201": {
        "Staff": [
            {
                "name": "קליין גריגורי",
                "email": "gregy.kl@technion.ac.il",
                "title": "מרצה - אחראי מקצוע"
            },
            {
                "name": "הרשקו דפנה",
                "email": "ae.ugsec@technion.ac.il",
                "title": "מרצה"
            },
            {
                "name": "אבני אור",
                "email": "oravni@campus.technion.ac.il",
                "title": "מתרגל - עם הרשאות מרצה אחראי"
            }
        ],
        "Exam_A": {
            "students": "61",
            "passFail": "59\/2",
            "passPercent": "97",
            "min": "25",
            "max": "94",
            "average": "80.246",
            "median": "82"
        },
        "Final_A": {
            "students": "61",
            "passFail": "60\/1",
            "passPercent": "98",
            "min": "36.25",
            "max": "94.9",
            "average": "82.995",
            "median": "84.7"
        },
        "Exam_B": {
            "students": "18",
            "passFail": "18\/0",
            "passPercent": "100",
            "min": "68",
            "max": "98",
            "average": "86.889",
            "median": "89.5"
        },
        "Final_B": {
            "students": "18",
            "passFail": "18\/0",
            "passPercent": "100",
            "min": "72.8",
            "max": "98.3",
            "average": "88.682",
            "median": "90.825"
        },
        "Finals": {
            "students": "77",
            "passFail": "76\/1",
            "passPercent": "99",
            "min": "36",
            "max": "98",
            "average": "85.013",
            "median": "86"
        }
    },
    "202101": {
        "Staff": [
            {
                "name": "יודילביץ גיל",
                "email": "gily@technion.ac.il",
                "title": "מרצה - אחראי מקצוע"
            },
            {
                "name": "אבני אור",
                "email": "oravni@campus.technion.ac.il",
                "title": "מתרגל - עם הרשאות מרצה אחראי"
            }
        ],
        "Exam_A": {
            "students": "70",
            "passFail": "52\/18",
            "passPercent": "74",
            "min": "12",
            "max": "103",
            "average": "65",
            "median": "68"
        },
        "Final_A": {
            "students": "70",
            "passFail": "60\/10",
            "passPercent": "86",
            "min": "34",
            "max": "101.75",
            "average": "73.551",
            "median": "76"
        },
        "Exam_B": {
            "students": "19",
            "passFail": "11\/8",
            "passPercent": "58",
            "min": "25",
            "max": "84",
            "average": "55.789",
            "median": "55"
        },
        "Final_B": {
            "students": "19",
            "passFail": "17\/2",
            "passPercent": "89",
            "min": "43",
            "max": "88",
            "average": "66.468",
            "median": "64.6"
        },
        "Finals": {
            "students": "85",
            "passFail": "81\/4",
            "passPercent": "95",
            "min": "44",
            "max": "100",
            "average": "74.965",
            "median": "76"
        }
    },
    "202001": {
        "Staff": [
            {
                "name": "יודילביץ גיל",
                "email": "gily@technion.ac.il",
                "title": "מרצה - אחראי מקצוע"
            },
            {
                "name": "אבני אור",
                "email": "oravni@campus.technion.ac.il",
                "title": "מתרגל - עם הרשאות מרצה אחראי"
            }
        ],
        "Final_A": {
            "students": "55",
            "passFail": "47\/8",
            "passPercent": "85",
            "min": "38.75",
            "max": "98.3",
            "average": "72.432",
            "median": "71.95"
        },
        "Final_B": {
            "students": "37",
            "passFail": "31\/6",
            "passPercent": "84",
            "min": "43.42",
            "max": "95.575",
            "average": "73.587",
            "median": "77.02"
        },
        "Finals": {
            "students": "77",
            "passFail": "70\/7",
            "passPercent": "91",
            "min": "43",
            "max": "98",
            "average": "75.883",
            "median": "77"
        }
    },
    "201901": {
        "Staff": [
            {
                "name": "יודילביץ גיל",
                "email": "gily@technion.ac.il",
                "title": "מרצה - אחראי מקצוע"
            },
            {
                "name": "צ'וייב ולדימיר",
                "email": "vovatch@campus.technion.ac.il",
                "title": "מתרגל - עם הרשאות מרצה אחראי"
            }
        ],
        "Final_A": {
            "students": "32",
            "passFail": "25\/7",
            "passPercent": "78",
            "min": "25.76",
            "max": "101.4",
            "average": "66.131",
            "median": "64.535"
        },
        "Final_B": {
            "students": "48",
            "passFail": "39\/9",
            "passPercent": "81",
            "min": "42.57",
            "max": "93.3",
            "average": "67.144",
            "median": "68.01"
        },
        "Finals": {
            "students": "65",
            "passFail": "58\/7",
            "passPercent": "89",
            "min": "43",
            "max": "100",
            "average": "68.862",
            "median": "69"
        }
    }
}