{"202201":{"Staff":[{"name":"ג'בארין מחמוד","email":"cvjmah@technion.ac.il","title":"מרצה - אחראי מקצוע"},{"name":"צאצאשוילי תמי","email":"tami@technion.ac.il","title":"סגל מנהלי - עם הרשאות מרצה אחראי"},{"name":"בלסברג עליזה","email":"aliza@technion.ac.il","title":"סגל מנהלי - עם הרשאות מרצה אחראי"},{"name":"לוינסקי יעל","email":"yaelly@technion.ac.il","title":"סגל מנהלי - עם הרשאות מרצה אחראי"},{"name":"מלכה אופירה","email":"ofiramalka@technion.ac.il","title":"סגל מנהלי - עם הרשאות מרצה אחראי"},{"name":"קובלר קרן","email":"kovlerk@technion.ac.il","title":"סגל מנהלי - עם הרשאות מרצה אחראי"},{"name":"בן-סימון ציפורה","email":"transeng@technion.ac.il","title":"סגל מנהלי - עם הרשאות מרצה אחראי"},{"name":"שביט שרית","email":"sarits@technion.ac.il","title":"סגל מנהלי - עם הרשאות מרצה אחראי"}],"Exam_A":{"students":"153","passFail":"54\/99","passPercent":"35","min":"0","max":"99","average":"45.098","median":"43"},"Final_A":{"students":"153","passFail":"54\/99","passPercent":"35","min":"0","max":"100","average":"46.876","median":"43"},"Exam_B":{"students":"107","passFail":"59\/48","passPercent":"55","min":"1","max":"99","average":"56.57","median":"55"},"Final_B":{"students":"107","passFail":"63\/44","passPercent":"59","min":"1","max":"99","average":"58.056","median":"60"},"Finals":{"students":"164","passFail":"112\/52","passPercent":"68","min":"1","max":"100","average":"61.354","median":"66"}},"202202":{"Staff":[{"name":"קרינסקי יורי","email":"karinski@technion.ac.il","title":"מרצה - אחראי מקצוע"},{"name":"שביט שרית","email":"sarits@technion.ac.il","title":"סגל מנהלי - עם הרשאות מרצה אחראי"},{"name":"בלסברג עליזה","email":"aliza@technion.ac.il","title":"סגל מנהלי - עם הרשאות מרצה אחראי"},{"name":"לוינסקי יעל","email":"yaelly@technion.ac.il","title":"סגל מנהלי - עם הרשאות מרצה אחראי"},{"name":"מלכה אופירה","email":"ofiramalka@technion.ac.il","title":"סגל מנהלי - עם הרשאות מרצה אחראי"},{"name":"צאצאשוילי תמי","email":"tami@technion.ac.il","title":"סגל מנהלי - עם הרשאות מרצה אחראי"},{"name":"בן-סימון ציפורה","email":"transeng@technion.ac.il","title":"סגל מנהלי - עם הרשאות מרצה אחראי"},{"name":"קובלר קרן","email":"kovlerk@technion.ac.il","title":"סגל מנהלי - עם הרשאות מרצה אחראי"}],"Final_A":{"students":"44","passFail":"18\/26","passPercent":"41","min":"14","max":"68","average":"45.386","median":"49"},"Finals":{"students":"44","passFail":"18\/26","passPercent":"41","min":"14","max":"70","average":"45.614","median":"49"}}}