{"201702":{"Staff":[{"name":"שפיר ארן","email":"oshapir@gmail.com,oshapir@technion.ac.il","title":"מתרגל - עם הרשאות מרצה אחראי"}],"Final_A":{"students":"66","passFail":"66\/0","passPercent":"100","min":"72","max":"100","average":"91.5","median":"92"},"Finals":{"students":"68","passFail":"68\/0","passPercent":"100","min":"72","max":"100","average":"91.588","median":"92"}},"201802":{"Staff":[{"name":"שפיר ארן","email":"oshapir@gmail.com,oshapir@technion.ac.il","title":"מתרגל - עם הרשאות מרצה אחראי"}],"Final_A":{"students":"62","passFail":"62\/0","passPercent":"100","min":"65","max":"100","average":"90.242","median":"92"},"Finals":{"students":"63","passFail":"63\/0","passPercent":"100","min":"65","max":"100","average":"90.19","median":"91"}}}