{"201501":{"Staff":[{"name":"מנלה אבשלום","email":"amanela@technion.ac.il","title":"מרצה - אחראי מקצוע"},{"name":"טיומקין סוניה","email":"sonyk.tmk@gmail.com","title":"מתרגל"}],"Exam_A":{"students":"11","passFail":"6\/5","passPercent":"55","min":"30","max":"79","average":"57.455","median":"54"},"Final_A":{"students":"11","passFail":"9\/2","passPercent":"82","min":"39","max":"86","average":"65.545","median":"62"},"Finals":{"students":"12","passFail":"12\/0","passPercent":"100","min":"59","max":"92","average":"72.083","median":"72"}},"201602":{"Staff":[{"name":"מנלה אבשלום","email":"amanela@technion.ac.il","title":"מרצה - אחראי מקצוע"},{"name":"בן עמי ירון","email":"yaronhab@gmail.com,yaronben@campus.technion.ac.il","title":"מתרגל"},{"name":"מזור לילך","email":"slilach@campus.technion.ac.il","title":"מתרגל"}],"Exam_A":{"students":"60","passFail":"44\/16","passPercent":"73","min":"16","max":"99","average":"64.733","median":"64"},"Final_A":{"students":"60","passFail":"46\/14","passPercent":"77","min":"24","max":"99","average":"68.3","median":"68"},"Exam_B":{"students":"27","passFail":"16\/11","passPercent":"59","min":"18","max":"81","average":"55.926","median":"59"},"Final_B":{"students":"27","passFail":"19\/8","passPercent":"70","min":"26","max":"84","average":"60.148","median":"63"},"Finals":{"students":"68","passFail":"60\/8","passPercent":"88","min":"26","max":"99","average":"70.529","median":"68.5"}},"201702":{"Staff":[{"name":"סטלנוב אוקסנה","email":"oksana.s@technion.ac.il","title":"מרצה - אחראי מקצוע"},{"name":"בן עמי ירון","email":"yaronhab@gmail.com,yaronben@campus.technion.ac.il","title":"מתרגל - עם הרשאות מרצה אחראי"}],"Exam_A":{"students":"67","passFail":"59\/8","passPercent":"88","min":"25","max":"98","average":"72.433","median":"76"},"Final_A":{"students":"67","passFail":"60\/7","passPercent":"90","min":"33","max":"98","average":"74.97","median":"78"},"Exam_B":{"students":"13","passFail":"10\/3","passPercent":"77","min":"31","max":"91","average":"70.154","median":"76"},"Final_B":{"students":"13","passFail":"10\/3","passPercent":"77","min":"38","max":"92","average":"72.692","median":"78"},"Finals":{"students":"71","passFail":"67\/4","passPercent":"94","min":"38","max":"98","average":"77.662","median":"79"}},"201801":{"Staff":[{"name":"סטלנוב אוקסנה","email":"oksana.s@technion.ac.il","title":"מרצה - אחראי מקצוע"}],"Exam_A":{"students":"15","passFail":"9\/6","passPercent":"60","min":"29","max":"93","average":"60.733","median":"55"},"Final_A":{"students":"15","passFail":"9\/6","passPercent":"60","min":"39","max":"94","average":"64.867","median":"65"},"Finals":{"students":"18","passFail":"16\/2","passPercent":"89","min":"44","max":"94","average":"71.778","median":"71"}},"201802":{"Staff":[{"name":"סטלנוב אוקסנה","email":"oksana.s@technion.ac.il","title":"מרצה - אחראי מקצוע"},{"name":"בן עמי ירון","email":"yaronhab@gmail.com,yaronben@campus.technion.ac.il","title":"מתרגל - עם הרשאות מרצה אחראי"}],"Exam_A":{"students":"54","passFail":"48\/6","passPercent":"89","min":"0","max":"97","average":"77.222","median":"82"},"Final_A":{"students":"53","passFail":"50\/3","passPercent":"94","min":"43","max":"95","average":"80.415","median":"84"},"Exam_B":{"students":"14","passFail":"7\/7","passPercent":"50","min":"18","max":"93","average":"49.929","median":"48.5"},"Final_B":{"students":"14","passFail":"7\/7","passPercent":"50","min":"18","max":"93","average":"53.429","median":"52"},"Finals":{"students":"63","passFail":"56\/7","passPercent":"89","min":"18","max":"100","average":"76.397","median":"83"}},"201902":{"Staff":[{"name":"מנלה אבשלום","email":"amanela@technion.ac.il","title":"מרצה - אחראי מקצוע"},{"name":"בן עמי ירון","email":"yaronhab@gmail.com,yaronben@campus.technion.ac.il","title":"מתרגל - עם הרשאות מרצה אחראי"}],"Exam_A":{"students":"53","passFail":"35\/18","passPercent":"66","min":"15","max":"97","average":"61.66","median":"61"},"Final_A":{"students":"53","passFail":"39\/14","passPercent":"74","min":"23","max":"97","average":"64.981","median":"64"},"Exam_B":{"students":"47","passFail":"25\/22","passPercent":"53","min":"0","max":"95","average":"55.915","median":"55"},"Final_B":{"students":"47","passFail":"32\/15","passPercent":"68","min":"8","max":"95","average":"59.553","median":"58"},"Finals":{"students":"78","passFail":"63\/15","passPercent":"81","min":"8","max":"97","average":"65.731","median":"64"}}}