[
  {
    "name": "גל ליאור",
    "email": "dl@tx.technion.ac.il,dl@technion.ac.il",
    "title": "מרצה"
  },
  {
    "name": "הורוביץ משה",
    "email": "horowitz@technion.ac.il",
    "title": "מרצה"
  },
  {
    "name": "סאיר גיא",
    "email": "guysayer@campus.technion.ac.il",
    "title": "מדריך מעבדה"
  },
  {
    "name": "טלמון אינה",
    "email": "ina@technion.ac.il",
    "title": "מדריך מעבדה"
  },
  {
    "name": "פלג נימרוד",
    "email": "nimrodp@technion.ac.il",
    "title": "מדריך מעבדה"
  }
]